{"training_subjects": [23, 12, 16, 13, 47, 32, 34, 33, 3, 7, 54, 57, 10, 11, 30, 4, 40, 36, 44, 21, 29, 18, 26, 51, 53, 9, 48, 50, 17, 8, 46, 55, 56, 15, 45, 59, 42, 22, 14, 49, 37, 38, 25, 39, 5, 6, 58, 1, 27, 19, 2, 43, 31, 52, 35, 20, 24], "testing_subjects": [41, 85, 28, 107], "training_files": ["../data/datasets/sequences/MI_RLH_T1.npy", "../data/datasets/sequences/MI_RLH_T2.npy"], "testing_files": ["../data/datasets/sequences/MI_RLH_T1.npy", "../data/datasets/sequences/MI_RLH_T2.npy"], "accuracy": 0.6799132823944092}