{"training_subjects": [12, 26, 6, 34, 35, 19, 54, 30, 48, 58, 52, 33, 49, 32, 25, 7, 18, 37, 40, 42, 15, 50, 14, 21, 3, 8, 45, 11, 17, 53, 13, 57, 51, 1, 38, 47, 5, 56, 55, 43, 31, 23, 44, 4, 29, 59, 20, 2, 16, 46, 22, 9, 27, 39, 36, 24, 10], "testing_subjects": [41, 85, 28, 107], "training_files": ["../data/datasets/sequences/MI_RLH_T1.npy", "../data/datasets/sequences/MI_RLH_T2.npy"], "testing_files": ["../data/datasets/sequences/MI_RLH_T1.npy", "../data/datasets/sequences/MI_RLH_T2.npy"], "accuracy": 0.6921965479850769}